Metadata-Version: 1.1
Name: komiku
Version: 0.0.2
Summary: komiku
Home-page: https://github.com/krypton-byte/komiku
Author: Krypton Byte
Author-email: galaxyvplus6434@gmail.com
License: MIT
Download-URL: https://github.com/krypton-byte/komiku/archive/0.0.2.tar.gz
Keywords: manga,pdf,downloader,komik,komiku
Platform: UNKNOWN
Classifier: Development Status :: 3 - Alpha
Classifier: Intended Audience :: Developers
Classifier: Topic :: Software Development :: Build Tools
Classifier: License :: OSI Approved :: MIT License
Classifier: Programming Language :: Python :: 3.8
Classifier: Programming Language :: Python :: 3.9
